foresite/JsonParser.py
foresite/JsonSerializer.py
foresite/RDFaSerializer.py
foresite/README.txt
foresite/__init__.py
foresite/conneg.py
foresite/ore.py
foresite/parser.py
foresite/serializer.py
foresite/tests.py
foresite/tripleStore.py
foresite/utils.py
google.foresite_toolkit-1.3.3.dist-info/DESCRIPTION.rst
google.foresite_toolkit-1.3.3.dist-info/METADATA
google.foresite_toolkit-1.3.3.dist-info/RECORD
google.foresite_toolkit-1.3.3.dist-info/WHEEL
google.foresite_toolkit-1.3.3.dist-info/metadata.json
google.foresite_toolkit-1.3.3.dist-info/top_level.txt
