Metadata-Version: 2.0
Name: google.foresite-toolkit
Version: 1.3.3
Summary: Library for constructing, parsing, manipulating and serializing OAI-ORE Resource Maps
Home-page: http://code.google.com/p/foresite-toolkit/
Author: Rob Sanderson
Author-email: azaroth@liv.ac.uk
License: BSD
Platform: UNKNOWN
Requires-Dist: lxml (==3.7.3)
Requires-Dist: rdflib (==4.2.2)
